LICENSE
MANIFEST.in
README.md
release_notes.txt
setup.py
valgrind-python.supp
valgrind.sh
D:/Programming/projects/pyaodbc/src/connection.c
D:/Programming/projects/pyaodbc/src/cursor.c
D:/Programming/projects/pyaodbc/src/get_data.c
D:/Programming/projects/pyaodbc/src/input_data.c
D:/Programming/projects/pyaodbc/src/linux.c
D:/Programming/projects/pyaodbc/src/module.c
D:/Programming/projects/pyaodbc/src/pyaodbc.pyi
pyaodbc.egg-info/PKG-INFO
pyaodbc.egg-info/SOURCES.txt
pyaodbc.egg-info/dependency_links.txt
pyaodbc.egg-info/top_level.txt
src/aodbc_types.h
src/connection.c
src/connection.h
src/cursor.c
src/cursor.h
src/get_data.c
src/get_data.h
src/headers.h
src/input_data.c
src/input_data.h
src/linux.c
src/linux.h
src/module.c
src/module.h
src/pyaodbc.pyi
tests/requirements.txt
tests/test_mssql.py