Metadata-Version: 2.1
Name: pyaodbc
Version: 0.2
Summary: Library for asynchronous connection and execution of queries to the database via ODBC driver
Home-page: https://github.com/SergioMorelo/pyaodbc
Download-URL: https://pypi.org/project/pyaodbc/
Author: Sergio Morello
Author-email: mail.Krik@gmail.com
Maintainer: Sergio Morello
Maintainer-email: mail.Krik@gmail.com
License: Apache license 2.0
Platform: Windows
Platform: Linux
Classifier: Framework :: AsyncIO
Classifier: License :: OSI Approved :: Apache Software License
Classifier: Operating System :: Microsoft :: Windows
Classifier: Operating System :: POSIX :: Linux
Classifier: Programming Language :: Python :: 3.7
Classifier: Programming Language :: Python :: 3.8
Classifier: Programming Language :: Python :: 3.9
Classifier: Programming Language :: Python :: 3.10
Classifier: Programming Language :: Python :: 3.11
Classifier: Topic :: Database
License-File: LICENSE
